{
  "details": {
    "bio": "韩非子（约公元前280年-前233年），韩国（今河南新郑）人，战国末期法家思想的集大成者。韩非是韩国公子，与李斯同学于荀子门下。他见韩国日渐衰弱，多次上书韩王建议改革，但未被采纳。于是发愤著书，写下了十余万字的《韩非子》。秦王嬴政读到韩非的文章后大为叹服，说'寡人得见此人与之游，死不恨矣'，于是发兵攻韩，迫韩王派韩非出使秦国。韩非到秦国后，遭到同学李斯的嫉妒和陷害，被迫服毒自杀于狱中。韩非综合了商鞅的'法'、申不害的'术'、慎到的'势'，建立了法、术、势相结合的完整法家理论体系，成为法家思想的集大成者。",
    "ideology": "法、术、势相结合的法治理论",
    "group": "法家",
    "timeline": [
      {
        "year": "约公元前280年",
        "event": "韩非出生于韩国",
        "type": "birth"
      },
      {
        "year": "约公元前255年",
        "event": "与李斯同师从荀子",
        "type": "milestone"
      },
      {
        "year": "约公元前240年",
        "event": "多次上书韩王，建议变法改革",
        "type": "milestone"
      },
      {
        "year": "约公元前235年",
        "event": "完成《韩非子》",
        "type": "work"
      },
      {
        "year": "公元前234年",
        "event": "秦王嬴政读到韩非文章，发兵攻韩求韩非",
        "type": "milestone"
      },
      {
        "year": "公元前233年",
        "event": "出使秦国，被李斯陷害，服毒自杀",
        "type": "death"
      }
    ],
    "works": [
      {
        "title": "韩非子",
        "type": "政治哲学著作",
        "summary": "韩非的代表作，共55篇，系统阐述了法、术、势相结合的法家理论。名篇有《五蠹》《孤愤》《说难》等。名句如'刑过不避大臣赏善不遗匹夫''世界则事异事异则备变'。"
      }
    ],
    "achievements": [
      "集法家思想之大成",
      "建立法、术、势相结合的理论体系",
      "其思想深刻影响了秦朝政治"
    ],
    "quotes": [
      "刑过不避大臣，赏善不遗匹夫",
      "世界则事异，事异则备变",
      "不期修古，不法常可"
    ],
    "appraisals": [
      "韩非之学，归本于黄老，而极于刑名——司马迁",
      "韩非子是法家思想的最高峰——近现代·哲学史家"
    ],
    "influence": "韩非子的思想深刻影响了秦朝及后世王朝的政治实践。其法治理论在历代王朝的统治中都有所体现。韩非的进化史观和改革精神在近代中国受到重新重视。",
    "controversies": [
      "韩非的极端集权思想被批评为专制主义的理论基础",
      "其人性论（性恶）过于消极"
    ],
    "mediaPortrayals": [
      "电视剧《大秦帝国》中有韩非形象",
      "电影《秦始皇》中韩非出场"
    ],
    "memorials": [
      "河南新郑韩非故里"
    ],
    "gallery": [],
    "trivia": [
      "韩非有口吃的毛病，但文笔雄辩有力，与口吃形成鲜明对比。",
      "韩非和李斯本是同学，但李斯因嫉妒而害死了韩非。"
    ],
    "references": [
      "《韩非子》",
      "《史记·老子韩非列传》（西汉·司马迁）"
    ],
    "baiduBaike": "https://baike.baidu.com/item/%E9%9F%A9%E9%9D%9E%E5%AD%90"
  },
  "relations": [
    {
      "targetId": "xun_zi",
      "relation": "师徒",
      "description": "韩非子师从荀子学习。"
    },
    {
      "targetId": "shen_dao",
      "relation": "思想来源",
      "description": "韩非吸收了慎到的势治思想。"
    },
    {
      "targetId": "shen_bu_hai",
      "relation": "思想来源",
      "description": "韩非吸收了申不害的术治思想。"
    }
  ]
}