{
  "details": {
    "bio": "柳永（约984—约1053），原名三变，字景庄，后改名永，字耆卿，崇安（今福建武夷山）人，北宋著名词人。因排行第七，世称柳七。早年屡试不第，流连于汴京歌楼酒肆，为歌女乐工填词。仁宗景佑元年（1034年）方中进士，时已年近五十。历任余杭县令、泗州判官等微职，晚年穷困潦倒，死时家无余财，由歌女们集资安葬。柳永是北宋前期最杰出的词人，对宋词发展有重要贡献：他大量创制慢词长调，极大拓展了词的体式和表现力。其词婉约细腻，以善写羁旅行役和都市繁华著称。有凡有井水处即能歌柳词的美誉。",
    "ideology": "",
    "group": "",
    "timeline": [
      {
        "year": "约984年",
        "event": "出生于崇安（今福建武夷山）",
        "type": "birth"
      },
      {
        "year": "约1015年",
        "event": "初入汴京参加科举，不第",
        "type": "milestone"
      },
      {
        "year": "约1034年",
        "event": "进士及第，时已年近五十",
        "type": "milestone"
      },
      {
        "year": "约1035年",
        "event": "任余杭县令",
        "type": "milestone"
      },
      {
        "year": "约1043年",
        "event": "创作《望海潮》，描绘杭州繁华",
        "type": "work"
      },
      {
        "year": "约1053年",
        "event": "去世，葬于襄阳",
        "type": "death"
      }
    ],
    "works": [
      {
        "title": "雨霖铃",
        "type": "词",
        "summary": "寒蝉凄切对长亭晚，执手相看泪眼竟无语凝噎，千古送别名篇。",
        "fullText": "寒蝉凄切，对长亭晚，骤雨初歇。都门帐饮无绪，留恋处，兰舟催发。执手相看泪眼，竟无语凝噎。念去去，千里烟波，暮霭沉沉楚天阔。多情自古伤离别，更那堪，冷落清秋节！今宵酒醒何处？杨柳岸，晓风残月。此去经年，应是良辰好景虚设。便纵有千种风情，更与何人说？"
      },
      {
        "title": "望海潮",
        "type": "词",
        "summary": "东南形胜三吴都会钱塘自古繁华，描写杭州风物，使金主完颜亮起投鞭渡江之志。"
      },
      {
        "title": "蝶恋花",
        "type": "词",
        "summary": "衣带渐宽终不悔为伊消得人憔悴，王国维以此喻古今之成大事业大学问者之第二境界。"
      },
      {
        "title": "八声甘州",
        "type": "词",
        "summary": "对潇潇暮雨洒江天一番洗清秋，苏轼称赞此词不减唐人高处。"
      },
      {
        "title": "鹤冲天",
        "type": "词",
        "summary": "忍把浮名换了浅斟低唱，因这首词得罪宋仁宗而落榜。"
      }
    ],
    "achievements": [
      "大量创制慢词长调，彻底改变了宋词的体式格局",
      "凡有井水处即能歌柳词，词作传播极广",
      "以通俗而不失雅致的词风影响后代婉约词人"
    ],
    "quotes": [
      "衣带渐宽终不悔，为伊消得人憔悴。——《蝶恋花》",
      "多情自古伤离别，更那堪冷落清秋节。——《雨霖铃》"
    ],
    "appraisals": [
      "凡有井水处，即能歌柳词。——叶梦得",
      "柳永词格固不高，然其写景处自工致。——苏轼"
    ],
    "influence": "柳永是宋词史上里程碑式的人物，他创制的慢词长调改变了唐五代以来以小令为主的格局。其以赋为词的手法深刻影响了周邦彦等后续词人。柳永在白话入词方面也有开创之功，其通俗化的词风使词真正走向民间。柳词中描写城市繁华和羁旅漂泊的新题材也极大地拓展了词的创作领域。",
    "mediaPortrayals": [
      "影视作品中柳永常以风流才子的形象出现",
      "民间传说柳永死后由歌女们集资安葬"
    ],
    "memorials": [
      "湖北襄阳柳永墓",
      "福建武夷山柳永纪念馆"
    ],
    "gallery": [],
    "trivia": [
      "柳永原名三变，出自《论语》君子有三变",
      "传说柳永因'忍把浮名换了浅斟低唱'而得罪宋仁宗",
      "柳永死后每年清明歌女们都会去祭扫"
    ],
    "references": [
      "《宋史·柳永传》",
      "《乐章集》柳永",
      "《柳永评传》"
    ],
    "baiduBaike": "https://baike.baidu.com/item/%E6%9F%B3%E6%B0%B8"
  },
  "relations": [
    {
      "targetId": "su_shi",
      "relation": "同时代词人",
      "description": "苏轼对柳永词有批评也有借鉴，\"不减唐人高处\"即是对柳永的称赞"
    },
    {
      "targetId": "zhou_bangyan",
      "relation": "词学传承",
      "description": "周邦彦继承柳永慢词的创作技法并加以雅化和格律化"
    }
  ],
  "styleName": "字耆卿，号柳七",
  "geo": {
    "lng": 118.5,
    "lat": 26.5
  }
}