{
  "details": {
    "bio": "马钧（约220年—280年），字德衡，三国时期扶风（今陕西兴平）人。三国时期著名的机械制造家和发明家，被誉为「天下名巧」。他出身贫寒，不善言辞，但精于机械设计和制造。他在魏国任博士、给事中等职。马钧一生有多项重大发明和改进：他改进了织绫机，将旧式五十综五十蹑的复杂织机改为十二蹑，提高效率五倍以上；他复原了已经失传的指南车，利用差动齿轮原理使车上木人始终指向南方；他创造了翻车（即龙骨水车），用于农业灌溉，成为此后中国农村广泛使用的提水工具；他还设计制造了转轮式发石车（连弩石车），可连续发射石块。马钧的机械创造代表了三国时期中国机械工程技术的最高水平。",
    "timeline": [
      {
        "year": "约220年",
        "event": "生于扶风（今陕西兴平）",
        "type": "birth"
      },
      {
        "year": "约245年",
        "event": "改进织绫机，提高织布效率",
        "type": "milestone"
      },
      {
        "year": "约250年",
        "event": "复原（改进）指南车",
        "type": "milestone"
      },
      {
        "year": "约255年",
        "event": "创制翻车（龙骨水车）用于农业灌溉",
        "type": "milestone"
      },
      {
        "year": "约260年",
        "event": "设计转轮式发石车等军事器械",
        "type": "milestone"
      },
      {
        "year": "约280年",
        "event": "去世",
        "type": "death"
      }
    ],
    "works": [
      {
        "title": "改进织绫机",
        "type": "机械发明",
        "summary": "将旧式织绫机从五十蹑简化为十二蹑，大幅提高生产效率"
      },
      {
        "title": "指南车",
        "type": "机械发明",
        "summary": "复原和改进指南车，利用差动齿轮原理使木人始终指南"
      },
      {
        "title": "翻车（龙骨水车）",
        "type": "机械发明",
        "summary": "创制用于农业灌溉的翻车，成为中国传统农具经典"
      },
      {
        "title": "转轮式发石车",
        "type": "军事器械",
        "summary": "可连续发射石块的攻城器械"
      }
    ],
    "achievements": [
      "改进织绫机，推动纺织技术进步",
      "复原指南车，展示了高超的机械设计水平",
      "创制翻车，为中国农业灌溉做出了重要贡献",
      "被誉为「天下名巧」"
    ],
    "quotes": [
      "「马先生之巧，虽古公输般、墨翟、王尔，近汉世张平子，不能过也。」——傅玄评马钧",
      "「天下之名巧也」——时人对马钧的赞誉"
    ],
    "appraisals": [
      "「马钧的翻车设计是中国古代最经典的提水机械，影响中国农业近两千年」——科技史界",
      "「马钧在中国机械史上的地位，相当于张衡在天文学史上的地位」——傅玄的评价"
    ],
    "influence": "马钧发明的翻车（龙骨水车）是中国古代最重要、最普及的农业灌溉机械，一直使用到20世纪中期。其差动齿轮原理在指南车上的运用，展示了中国古代机械设计的高度智慧。马钧的机械创造成就直接影响了后世中国农业和手工业的发展。",
    "mediaPortrayals": [],
    "memorials": [],
    "gallery": [],
    "trivia": [
      "马钧不善言辞，但精于机械制造，傅玄曾为他撰写长篇传文",
      "翻车（龙骨水车）一直使用到20世纪，部分地区至今仍在使用",
      "马钧复原的指南车被怀疑是否为真正的差动齿轮原理，学术界有讨论"
    ],
    "references": [
      "傅玄《马先生传》",
      "《三国志·魏书·方技传》",
      "刘仙洲《中国机械工程发明史》"
    ],
    "baiduBaike": "https://baike.baidu.com/item/%E9%A9%AC%E9%92%A7"
  },
  "relations": [
    {
      "targetId": "lu_ban",
      "relation": "机械发明传承",
      "description": "马钧继承了鲁班的工匠传统，在中国机械制造史上被称为「天下名巧」"
    },
    {
      "targetId": "zhang_heng",
      "relation": "机械制造传承",
      "description": "马钧和张衡都是中国古代杰出的机械制造家，指南车的复原展现了和张衡一样卓越的机械智慧"
    }
  ],
  "styleName": "字德衡",
  "geo": {
    "陕西兴平": [
      108.5,
      34.3
    ]
  }
}