{
  "details": {
    "bio": "夏圭（约1190年—1240年），字禹玉，钱塘（今浙江杭州）人。南宋著名山水画家，南宋四家之一。宋宁宗时曾任画院待诏。夏圭师法李唐、马远，但形成了自己独特的风格。他善于作半边构图，画面往往只画半边山水，留下大片空白，被称为「夏半边」。与马远的刚劲相比，夏圭的风格更偏清刚爽利，用笔更加简洁。他擅长水墨画，墨色变化丰富，将斧劈皴与水晕墨章相结合，创造出清旷悠远的意境。夏圭还长于长卷创作，代表作《溪山清远图》是南宋山水长卷的杰出代表。夏圭与马远共同将南宋院体山水推向极致，在中日绘画史上都占有重要地位。",
    "ideology": "简洁清旷，水墨淋漓；半边取景，画有尽而意无穷",
    "group": "南宋四家",
    "timeline": [
      {
        "year": "约1190年",
        "event": "生于钱塘（今浙江杭州）",
        "type": "birth"
      },
      {
        "year": "约1210年",
        "event": "任画院待诏",
        "type": "milestone"
      },
      {
        "year": "约1220年",
        "event": "山水画风格成熟",
        "type": "milestone"
      },
      {
        "year": "约1225年",
        "event": "创作《溪山清远图》",
        "type": "work"
      },
      {
        "year": "约1230年",
        "event": "创作《西湖柳艇图》",
        "type": "work"
      },
      {
        "year": "约1240年",
        "event": "去世",
        "type": "death"
      }
    ],
    "works": [
      {
        "title": "《溪山清远图》",
        "type": "画作",
        "summary": "纸本水墨山水长卷，夏圭最著名的代表作"
      },
      {
        "title": "《西湖柳艇图》",
        "type": "画作",
        "summary": "绢本设色山水画"
      },
      {
        "title": "《遥岑烟霭图》",
        "type": "画作",
        "summary": "绢本水墨山水画"
      },
      {
        "title": "《雪堂客话图》",
        "type": "画作",
        "summary": "绢本设色山水人物画"
      }
    ],
    "achievements": [
      "南宋四家之一，与马远并称「马夏」",
      "创「夏半边」的构图风格",
      "对中日山水画产生深远影响"
    ],
    "quotes": [
      "「夏圭画，笔意苍古，墨气淋漓」——历代画评",
      "「马一角，夏半边」——对南宋院体构图的经典概括"
    ],
    "appraisals": [
      "「夏圭的《溪山清远图》是南宋山水长卷的杰作」——美术史学界",
      "「夏圭画中之墨，如春雨之润物」——历代画评"
    ],
    "influence": "夏圭与马远共同将南宋院体山水画推向历史巅峰。「马夏」画风对后世影响极大，尤其是对日本水墨画的启迪作用难以估量。日本画圣雪舟的山水画风格直接受益于「马夏」的传统。",
    "mediaPortrayals": [],
    "memorials": [
      "台湾台北：台北故宫博物院藏《溪山清远图》"
    ],
    "gallery": [],
    "trivia": [
      "「夏半边」的构图方式对日本茶道美学中的「侘寂」理念产生了影响",
      "夏圭的《溪山清远图》是纸本水墨，与马远多用绢本不同"
    ],
    "references": [
      "《画继》",
      "《南宋院画录》"
    ],
    "baiduBaike": "https://baike.baidu.com/item/%E5%A4%8F%E5%9C%AD"
  },
  "relations": [
    {
      "targetId": "ma_yuan",
      "relation": "南宋四家",
      "description": "夏圭与马远并称「马夏」，两人共同确立了南宋院体山水的经典面貌"
    },
    {
      "targetId": "li_tang",
      "relation": "师承关系",
      "description": "夏圭继承李唐开创的斧劈皴传统并发展出清刚爽利的个人风格"
    }
  ]
}